{
    "root": {
        "screen": [
            {
                "name": "ecran1",
                "defaultPage": true,
                "style": {
                    "color": "#6897bb",
                    "align": "center"
                },
                "content": [
                    {
                        "block": {
                            "style": {
                                "align": "center"
                            },
                            "content": [
                                {
                                    "text": {
                                        "style": {
                                            "color": "#ff0000",
                                            "decoration": "underline"
                                        },
                                        "textValue": "hello world"
                                    }
                                },
                                {
                                    "link": {
                                        "targetValue": "ecran1",
                                        "content": [
                                            {
                                                "text": {
                                                    "textValue": "lien vers ecran 1"
                                                }
                                            }
                                        ]
                                    }
                                },
                                {
                                    "link": {
                                        "targetValue": "http://youtube.com",
                                        "external": true,
                                        "content": [
                                            {
                                                "text": {
                                                    "textValue": "lien externe vers youtube"
                                                }
                                            }
                                        ]
                                    }
                                },
                                {
                                    "block": {
                                        "style": {
                                            "color": "#0000ff"
                                        },
                                        "content": [
                                            {
                                                "text": {
                                                    "textValue": "some nested text"
                                                }
                                            }
                                        ]
                                    }
                                },
                                {
                                    "text": {
                                        "style": {
                                            "color": "#ff0000"
                                        },
                                        "textValue": "other text"
                                    }
                                }
                            ]
                        }
                    },
                    {
                        "block": {
                            "style": {
                                "align": "center"
                            },
                            "content": [
                                {
                                    "text": {
                                        "style": {
                                            "color": "#008000",
                                            "decoration": "italic"
                                        },
                                        "textValue": "hello world1"
                                    }
                                },
                                {
                                    "text": {
                                        "style": {
                                            "color": "#add8e6"
                                        },
                                        "textValue": "hello world2"
                                    }
                                }
                            ]
                        }
                    }
                ]
            },
            {
                "name": "ecran2",
                "style": {
                    "color": "#6897bb",
                    "align": "center"
                },
                "content": [
                    {
                        "block": {
                            "style": {
                                "align": "center"
                            },
                            "content": [
                                {
                                    "text": {
                                        "style": {
                                            "color": "#ff0000",
                                            "decoration": "underline"
                                        },
                                        "textValue": "hello world"
                                    }
                                },
                                {
                                    "block": {
                                        "style": {
                                            "color": "#0000ff"
                                        },
                                        "content": [
                                            {
                                                "text": {
                                                    "textValue": "some nested text"
                                                }
                                            }
                                        ]
                                    }
                                },
                                {
                                    "text": {
                                        "style": {
                                            "color": "#ff0000"
                                        },
                                        "textValue": "other text"
                                    }
                                }
                            ]
                        }
                    },
                    {
                        "block": {
                            "style": {
                                "align": "center"
                            },
                            "content": [
                                {
                                    "text": {
                                        "style": {
                                            "color": "#008000",
                                            "decoration": "italic"
                                        },
                                        "textValue": "hello world1"
                                    }
                                },
                                {
                                    "text": {
                                        "style": {
                                            "color": "#add8e6"
                                        },
                                        "textValue": "hello world2"
                                    }
                                }
                            ]
                        }
                    }
                ]
            }
        ]
    }
}
